Metadata-Version: 2.1
Name: xremovebg
Version: 0.1
Summary: RemoveBg Scraper without apikey
Home-page: https://github.com/krypton-byte/removebg
Author: Krypton Byte
Author-email: galaxyvplus6434@gmail.com
License: MIT
Keywords: Removebg,Scrapper,Without apikey
Platform: UNKNOWN
Classifier: Development Status :: 3 - Alpha
Classifier: Intended Audience :: Developers
Classifier: Topic :: Software Development :: Build Tools
Classifier: License :: OSI Approved :: MIT License
Classifier: Programming Language :: Python :: 3.8
Classifier: Programming Language :: Python :: 3.9
